cfeconfig/__init__.py
cfeconfig/config.py
cfeconfig-0.5.1.dist-info/LICENSE
cfeconfig-0.5.1.dist-info/WHEEL
cfeconfig-0.5.1.dist-info/METADATA
cfeconfig-0.5.1.dist-info/RECORD
